texttables/__init__.py
texttables/dialect.py
texttables/errors.py
texttables/dynamic/__init__.py
texttables/dynamic/_writer.py
texttables/fixed/__init__.py
texttables/fixed/_reader.py
texttables/fixed/_writer.py
texttables-1.0.1.dist-info/DESCRIPTION.rst
texttables-1.0.1.dist-info/METADATA
texttables-1.0.1.dist-info/RECORD
texttables-1.0.1.dist-info/WHEEL
texttables-1.0.1.dist-info/metadata.json
texttables-1.0.1.dist-info/top_level.txt
