Metadata-Version: 2.0
Name: texttables
Version: 1.0.1
Summary: A Python module for parsing and writing text-based tables
Home-page: https://github.com/Taywee/texttables
Author: Taylor C. Richberger <tcr@absolute-performance.com>
Author-email: tcr@absolute-performance.com
License: MIT
Platform: UNKNOWN
Classifier: Intended Audience :: Developers
Classifier: License :: OSI Approved :: MIT License
Classifier: Natural Language :: English
Classifier: Programming Language :: Python :: 2
Classifier: Programming Language :: Python :: 2.7
Classifier: Programming Language :: Python :: 3
Classifier: Programming Language :: Python :: 3.5
Classifier: Programming Language :: Python :: Implementation :: CPython
Classifier: Topic :: Software Development :: Libraries :: Python Modules
Requires-Dist: six
